survey_report_generator/__init__.py
survey_report_generator/databases.py
survey_report_generator/databases_summary.py
survey_report_generator/date_time.py
survey_report_generator/download_files.py
survey_report_generator/fesm.py
survey_report_generator/figures_utils.py
survey_report_generator/filter_utils.py
survey_report_generator/filter_utils_summary.py
survey_report_generator/g_drive_utils.py
survey_report_generator/generate_report.py
survey_report_generator/koala_habitat.py
survey_report_generator/pct.py
survey_report_generator/report-template.docx
survey_report_generator/report.py
survey_report_generator/storage.json
survey_report_generator/summary.py
survey_report_generator/tables.py
survey_report_generator-0.0.18.dist-info/LICENSE
survey_report_generator-0.0.18.dist-info/METADATA
survey_report_generator-0.0.18.dist-info/WHEEL
survey_report_generator-0.0.18.dist-info/RECORD
