Metadata-Version: 2.1
Name: survey-report-generator
Version: 0.0.18
Summary: A tool to generate survey reports from collected data
Home-page: https://github.com/nsw-wildlife-drone-hub/report-generator
License: MIT
Author: Oliver Hahn
Author-email: oliver.a.hahn@gmail.com
Requires-Python: >=3.7
Classifier: License :: OSI Approved :: MIT License
Classifier: Operating System :: OS Independent
Classifier: Programming Language :: Python :: 3
Classifier: Programming Language :: Python :: 3.7
Classifier: Programming Language :: Python :: 3.8
Classifier: Programming Language :: Python :: 3.9
Classifier: Programming Language :: Python :: 3.10
Classifier: Programming Language :: Python :: 3.11
Requires-Dist: contextily (>=1.3.0,<2.0.0)
Requires-Dist: docxtpl (>=0.11.5,<0.12.0)
Requires-Dist: fiona
Requires-Dist: gdown (>=4.7.1,<5.0.0)
Requires-Dist: geopandas (>=0.9.0,<0.10.0)
Requires-Dist: google-api-python-client (>=2.86.0,<3.0.0)
Requires-Dist: httplib2 (>=0.22.0,<0.23.0)
Requires-Dist: numpy (>=1.24.3,<2.0.0)
Requires-Dist: oauth2client (>=4.1.3,<5.0.0)
Requires-Dist: pandas (>=2.0.1,<3.0.0)
Requires-Dist: shapely (>=2.0.1,<3.0.0)
